crackwifi/__init__.py
crackwifi-0.1.1.dist-info/COPYING
crackwifi-0.1.1.dist-info/WHEEL
crackwifi-0.1.1.dist-info/METADATA
crackwifi-0.1.1.dist-info/RECORD
