Metadata-Version: 2.1
Name: crackwifi
Version: 0.1.1
Summary: Automate cracking wifis using reaver
Home-page: https://github.com/4thel00z/crackwifi
License: GPL-3
Author: 4thel00z
Author-email: 4thel00z@gmail.com
Requires-Python: >=3.7,<4.0
Classifier: License :: Other/Proprietary License
Classifier: Programming Language :: Python :: 3
Classifier: Programming Language :: Python :: 3.7
Classifier: Programming Language :: Python :: 3.8
Classifier: Programming Language :: Python :: 3.9
Requires-Dist: plumbum (>=1.7.0,<2.0.0)
